arithmic/__init__.py
arithmic/__main__.py
arithmic/cli.py
arithmic/provider.py
arithmic/rag_core.py
arithmic/repl.py
arithmic-0.1.0.dist-info/METADATA
arithmic-0.1.0.dist-info/WHEEL
arithmic-0.1.0.dist-info/entry_points.txt
arithmic-0.1.0.dist-info/top_level.txt
arithmic-0.1.0.dist-info/RECORD
