Metadata-Version: 2.4
Name: arithmic
Version: 0.1.0
Summary: Arithmic — Groq-powered RAG agent that knows your files and code
Author: Arithmic AI
License: Apache-2.0
Requires-Python: >=3.9
Requires-Dist: groq>=0.9.0
Requires-Dist: ollama>=0.3.0
Requires-Dist: typer>=0.12.0
Requires-Dist: qdrant-client>=1.9.0
Requires-Dist: sentence-transformers>=3.0.0
Requires-Dist: pypdf>=4.2.0
Requires-Dist: docx2txt>=0.8
Requires-Dist: tqdm>=4.66.0
